experiments/classifier/classifier.py
experiments/judge_bench/cola.py
experiments/judgement_day/create_test_data.py
experiments/judgement_day/llmonpy_ranker.py
experiments/judgement_day/llmonpy_validator.py
experiments/judgement_day/run_test.py
experiments/judgement_day/test_question.py
experiments/threaded_nian/threaded_nian.py
experiments/title_write/gen_title.py
experiments/title_write/title_write.py
experiments/title_write/tune_eval.py
llmonpy/__init__.py
llmonpy/config.py
llmonpy/jsony.py
llmonpy/llm_client.py
llmonpy/llmon_pypeline.py
llmonpy/llmonpy_cli.py
llmonpy/llmonpy_execute.py
llmonpy/llmonpy_gar.py
llmonpy/llmonpy_prompt.py
llmonpy/llmonpy_step.py
llmonpy/llmonpy_team.py
llmonpy/llmonpy_tournament.py
llmonpy/llmonpy_trace_store.py
llmonpy/llmonpy_util.py
llmonpy/system_services.py
llmonpy/system_startup.py
llmonpy/trace_log.py
llmonpy/api/__init__.py
llmonpy/api/api.py
llmonpy/api/api_app.py
llmonpy/api/api_config.py
llmonpy/api/api_system_startup.py
llmonpy/api/sys_path.py
llmonpy/api/static/favicon.ico
llmonpy/api/static/index.html
llmonpy/api/static/assets/Default-DlIij-Ys.css
llmonpy/api/static/assets/Default-DlJJrENM.js
llmonpy/api/static/assets/QbawaViewer-DQOi_380.js
llmonpy/api/static/assets/TraceViewer-Bzw2OvNg.css
llmonpy/api/static/assets/TraceViewer-CaqaGAHF.js
llmonpy/api/static/assets/VAvatar-DSQ_vJpX.css
llmonpy/api/static/assets/VAvatar-DcsRgvnP.js
llmonpy/api/static/assets/VCard-BGihEtQu.css
llmonpy/api/static/assets/VCard-BPKJkjND.js
llmonpy/api/static/assets/index-BQueRJq9.css
llmonpy/api/static/assets/index-CUebPUEO.js
llmonpy/api/static/assets/materialdesignicons-webfont-CYDMK1kx.woff2
llmonpy/api/static/assets/materialdesignicons-webfont-CgCzGbLl.woff
llmonpy/api/static/assets/materialdesignicons-webfont-D3kAzl71.ttf
llmonpy/api/static/assets/materialdesignicons-webfont-DttUABo4.eot
llmonpy/api/static/assets/scopeId-HBOZp6ca.css
llmonpy/api/static/assets/scopeId-hPYXQs06.js
llmonpy/example/read_tourney_result_file.py
llmonpy-0.1.35.dist-info/LICENSE
llmonpy-0.1.35.dist-info/METADATA
llmonpy-0.1.35.dist-info/WHEEL
llmonpy-0.1.35.dist-info/entry_points.txt
llmonpy-0.1.35.dist-info/top_level.txt
llmonpy-0.1.35.dist-info/RECORD
