Metadata-Version: 2.2
Name: llmonpy
Version: 0.1.35
Summary: AI pipeline framework for Python.
Author-email: Tom Burns <public@llmonpy.ai>
License: MIT License
Project-URL: Homepage, https://github.com/llmonpy/llmonpy
Project-URL: Issues, https://github.com/llmonpy/llmonpy/issues
Classifier: Programming Language :: Python :: 3
Classifier: License :: OSI Approved :: MIT License
Classifier: Operating System :: OS Independent
Requires-Python: >=3.12
License-File: LICENSE
Requires-Dist: google-generativeai
Requires-Dist: openai
Requires-Dist: mistralai>=1.0
Requires-Dist: anthropic
Requires-Dist: fireworks-ai
Requires-Dist: together
Requires-Dist: groq
Requires-Dist: ai21
Requires-Dist: ratellmiter-ai
Requires-Dist: jinja2
Requires-Dist: flask
Requires-Dist: flask_cors
Requires-Dist: matplotlib
